{
  "schemaVersion": 1,
  "id": "fpssharp",
  "version": "${version}",

  "name": "FPS#",
  "description": "THE MOST GOODEST FPSER EVER!!!!!!!!!!!!!",
  "authors": [
    "SudoDistnat"
  ],
  "contact": {
    "homepage": "APRIL FOOLS!",
    "sources": "APRIL FOOLS!"
  },

  "license": "Closed Source >:D",
  "icon": "assets/modid/icon.png",

  "environment": "*",
  "entrypoints": {
    "main": [
      "eyeoh.geethoob.sudodistnat.EFPEEES"
    ]
  },
  "mixins": [
    "dafpsdoe.mixins.json"
  ],

  "depends": {
    "fabricloader": ">=0.13.3",
    "minecraft": "1.18.x",
    "java": ">=17"
  },
  "suggests": {
    "linux-nvidia-graphics": "340.107.0"
  }
}
